visma_administration/__init__.py
visma_administration/api.py
visma_administration-0.6.2.dist-info/LICENSE.txt
visma_administration-0.6.2.dist-info/METADATA
visma_administration-0.6.2.dist-info/WHEEL
visma_administration-0.6.2.dist-info/top_level.txt
visma_administration-0.6.2.dist-info/RECORD
