Metadata-Version: 2.1
Name: visma-administration
Version: 0.6.2
Summary: API for Visma Administration 200/500/1000/2000
Home-page: https://github.com/viktor2097/visma-administration
Download-URL: https://github.com/viktor2097/visma-administration/archive/0.6.2.tar.gz
Author: Viktor Johansson
Author-email: dpedesigns@hotmail.com
License: MIT
Keywords: visma
Classifier: Development Status :: 3 - Alpha
Classifier: Intended Audience :: Developers
Classifier: License :: OSI Approved :: MIT License
Classifier: Programming Language :: Python :: 3
License-File: LICENSE.txt
Requires-Dist: pythonnet >=2.5.1
